pycat/__init__.py
pycat/cli.py
pycat/config.py
pycat/imcat.py
pycat/xterm_colors.py
pycat_real-0.35.dist-info/METADATA
pycat_real-0.35.dist-info/WHEEL
pycat_real-0.35.dist-info/entry_points.txt
pycat_real-0.35.dist-info/top_level.txt
pycat_real-0.35.dist-info/RECORD
