Metadata-Version: 2.1
Name: pycat-real
Version: 0.35
Summary: Something like print, but for images...
Home-page: https://github.com/PiotrDabkowski/pycat
Author: Piotr Dabkowski
Author-email: piodrus@gmail.com
License: MIT
Platform: UNKNOWN
Requires-Dist: Pillow
Requires-Dist: numpy
Requires-Dist: six
Requires-Dist: click
